RISC-V-Single-Cycle/RTL/loadmem.sv
module loadmem #(
    parameter D_WIDTH = 32
) (
    input  logic [        2:0] addrmode,
    input  logic [        1:0] selectbytes,  //instruction[1:0]%4 in cpu.sv
    input  logic [D_WIDTH-1:0] ramout,
    output logic [D_WIDTH-1:0] read_data
);

  always_comb begin
    case (addrmode)
      3'b000: begin  //load byte signed
        case(selectbytes) //read_data = {{5'd24{ramout[selectbytes*8 + 7]}}, ramout[selectbytes*8 + 7:selectbytes*8]};
          2'b00: read_data = {{5'd24{ramout[7]}}, ramout[7:0]};  //select byte 00
          2'b01: read_data = {{5'd24{ramout[15]}}, ramout[15:8]};  //select byte 01
          2'b10: read_data = {{5'd24{ramout[23]}}, ramout[23:16]};  //select byte 10
          2'b11: read_data = {{5'd24{ramout[31]}}, ramout[31:24]};  //select byte 11
        endcase
      end
      3'b001: begin  //load half signed
        case(selectbytes) //read_data = (selectbytes!=3)?{{5'd16{ramout[selectbytes*8 + 15]}}, ramout[selectbytes*8 + 15:selectbytes*8]}:0;
          2'b00: read_data = {{5'd16{ramout[15]}}, ramout[15:0]};  //select byte 00
          2'b01: read_data = {{5'd16{ramout[23]}}, ramout[23:8]};  //select byte 01
          2'b10: read_data = {{5'd16{ramout[31]}}, ramout[31:16]};  //select byte 10
          2'b11: read_data = 0;  //complete all cases
        endcase
      end
      3'b100: begin  //load byte unsigned
        case (selectbytes)  //read_data = {{5'd24{0}}, ramout[selectbits*8 + 7:selectbits*8]};
          2'b00: read_data = {{24'b0}, ramout[7:0]};  //select byte 00
          2'b01: read_data = {{24'b0}, ramout[15:8]};  //select byte 01
          2'b10: read_data = {{24'b0}, ramout[23:16]};  //select byte 10
          2'b11: read_data = {{24'b0}, ramout[31:24]};  //select byte 11
        endcase
      end
      3'b101: begin  //load half unsigned
        case(selectbytes) //read_data = (selectbits!=3)?{{4'd16{ramout[selectbits*8 + 15]}}, ramout[selectbits*8 + 15:selectbits*8]}:0
          2'b00: read_data = {{16'b0}, ramout[15:0]};  //select byte 00
          2'b01: read_data = {{16'b0}, ramout[23:8]};  //select byte 01
          2'b10: read_data = {{16'b0}, ramout[31:16]};  //select byte 10
          2'b11: read_data = 0;  //complete all cases
        endcase
      end
      3'b010: read_data = ramout;  //load word

      default: begin
        read_data = ramout;  //load word
      end
    endcase
  end

  // always_ff @(posedge clk) begin
  //   $display("read_data: %h", read_data, " ramout: %h", ramout);
  // end

endmodule

RISC-V-Single-Cycle/RTL/ram.sv
module ram #(
  parameter ADDRESS_WIDTH = 32, 
            DATA_WIDTH = 8                         //byte addressed design
)(
  input logic                      clk, write_enable,    //clock and write enable
  input logic  [ADDRESS_WIDTH-1:0] address,        //address
  input logic  [             31:0] ramin,     //write data input
  output logic [             31:0] ramout       //data output
);

  logic [DATA_WIDTH-1:0] ram_array [32'h00001ffff : 32'h0000000]; //according to memory map

  initial begin                                                //initialise with all zeros
    for (int i = 32'h00001000; i < $size(ram_array); i++) begin
      ram_array[i] = 8'b0;
    end
    $readmemh("./mem/<filename>.mem", ram_array, 32'h10000); // ....mem is the pdf mem file to test
  end

  always_comb begin 
    ramout = {{ram_array[address+3]}, {ram_array[address+2]}, {ram_array[address+1]}, {ram_array[address]}};  
  end

  always_ff @(posedge clk) begin
    if(write_enable) begin
      ram_array[address]   <= ramin[7:0];
      ram_array[address+1] <= ramin[15:8];
      ram_array[address+2] <= ramin[23:16];
      ram_array[address+3] <= ramin[31:24];
    end
  end

endmodule

RISC-V-Single-Cycle/RTL/storemem.sv
module storemem #(
    parameter DATA_WIDTH = 32
)(
    input  logic [           2:0] addrmode,
    input  logic [           1:0] selectbytes,
    input  logic [DATA_WIDTH-1:0] ramout, write_data,     //output of ram and write data from register
    output logic [DATA_WIDTH-1:0] ramdin        //input of ram
);

  always_comb begin
    case (addrmode)
      3'b000:  // store byte
      case (selectbytes)
        2'b00: ramdin = {ramout[31:8], write_data[7:0]};  // select first byte
        2'b01: ramdin = {ramout[31:16], write_data[7:0], ramout[7:0]};  // select second byte
        2'b10: ramdin = {ramout[31:24], write_data[7:0], ramout[15:0]};  // select third byte
        2'b11: ramdin = {write_data[7:0], ramout[23:0]};  // select fourth byte
      endcase

      3'b001:
      case (selectbytes)  // store half
        2'b00: ramdin = {ramout[31:16], write_data[15:0]};  // select first byte
        2'b01: ramdin = {ramout[31:24], write_data[15:0], ramout[7:0]};  // select second byte
        2'b10: ramdin = {write_data[15:0], ramout[15:0]};  // select third byte
        2'b11: ramdin = 0;  // complete all cases
      endcase

      3'b010: ramdin = write_data;  // store word

      default: begin
        ramdin = write_data;  // store word
      end
    endcase
  end

endmodule

RISC-V-Single-Cycle/RTL/data_memory.sv
module data_memory #(
  parameter ADDRESS_WIDTH = 32,
            DATA_WIDTH = 32
)(  
    input  logic                     clk, write_enable, 
    input  logic [              2:0] addrmode,
    input  logic [              1:0] selectbytes,
    input  logic [   DATA_WIDTH-1:0] write_data,   //write data from register
    input  logic [ADDRESS_WIDTH-1:0] address,
    output logic [ADDRESS_WIDTH-1:0] read_data
);

logic [DATA_WIDTH-1:0] ramout, ramin;

storemem storemem(
  .addrmode(addrmode),
  .selectbytes(selectbytes),
  .ramout(ramout),
  .write_data(write_data),
  .ramdin(ramin)
);

ram ram(
  .clk(clk),
  .write_enable(write_enable),
  .address(address),
  .ramin(ramin),
  .ramout(ramout)
);

loadmem loadmem(
  .addrmode(addrmode),
  .selectbytes(selectbytes),
  .ramout(ramout),
  .read_data(read_data)
);

endmodule

RISC-V-Single-Cycle/rf.sv
module rf #(
    parameter  A_WIDTH = 5,
                D_WIDTH = 32
) (
    input logic clk,
    input logic we3,
    input logic [A_WIDTH-1:0] ad1,
    input logic [A_WIDTH-1:0] ad2,
    input logic [A_WIDTH-1:0] ad3,
    input logic [D_WIDTH-1:0] wd3,
    output logic [D_WIDTH-1:0] a0,
    output logic [D_WIDTH-1:0] rd1,
    output logic [D_WIDTH-1:0] rd2,
    input logic trigger
);

    logic [D_WIDTH-1:0] rf_array [2**A_WIDTH-1:0];

    always_comb begin
        rd1 = rf_array[ad1];
        rd2 = rf_array[ad2];
    end

    initial begin
        for (int i = 0; i < $size(rf_array); i++) begin
            rf_array[i] = 32'h0000;
        end
    end

    assign a0 = rf_array[10];


    always_ff @(posedge clk) begin
        // $display("x8: %h\t", rf_array[8], " a0:%h \t", a0 ," a1: %h\t", rf_array[11], " a2: %h\t", rf_array[12], "a3: %h\t", rf_array[13], "a4: %h\t", rf_array[14], "a5: %h\t", rf_array[15], "a6: %h\t", rf_array[16]);
        rf_array[9] <= {{31'b0}, trigger};
        if(we3) rf_array[ad3] <= wd3; 
    end
    
    
    
endmodule

RISC-V-Single-Cycle/RTL/alu.sv
module alu #(
    parameter D_WIDTH = 32
) (
    input logic alusrc,
    input logic [3:0] aluctrl,
    input logic [D_WIDTH-1:0] aluop1, immop, regop2,
    output logic [D_WIDTH-1:0] aluout,
    output logic eq
);

  logic [D_WIDTH-1:0] aluop2;

  always_comb begin
    aluop2  = alusrc ? immop : regop2;

    case (aluctrl)
      4'b0000: aluout = aluop1 + aluop2;
      4'b1000: aluout = aluop1 - aluop2;
      4'b0001: aluout = aluop1 << aluop2;  //shift left logic
      4'b0010: aluout = {{31'b0}, {(signed'(aluop1) < signed'(aluop2))}}; //set less than
      4'b0011: aluout = {{31'b0}, {(aluop1 < aluop2)}};  //set less than uns
      4'b0100: aluout = aluop1 ^ aluop2;
      4'b0101: aluout = aluop1 >> aluop2;  //shift right logical 
      4'b1101: aluout = $signed(aluop1) >>> aluop2[4:0];  // shift right arr
      4'b0110: aluout = aluop1 | aluop2;
      4'b0111: aluout = aluop1 & aluop2;
      4'b1111: aluout = aluop2;
      default: aluout = 0;
    endcase
  end

  always_comb begin
    case (aluctrl)
      4'b0100: eq = (aluout != 0);
      4'b0010: eq = aluout[0];
      default: eq = aluout[0];
    endcase
  end

  // always_ff @(posedge clk) begin
  //   $display("aluout[0]: %h", aluout[0],, " eq: %h", eq);
  // end

endmodule

RISC-V-Single-Cycle/RTL/signextender.sv
module signextender (
    input  logic [31:7] instruction,
    input  logic [ 2:0] immsrc,
    output logic [31:0] immop
    // input logic clk
);
  
  always_comb begin
    case (immsrc)
      3'b000: immop = {{20{instruction[31]}}, instruction[31:20]};  // immediate
      3'b001: immop = {instruction[31:12], {12'b0}};  // upper immediate
      3'b010: immop = {{20{instruction[31]}}, instruction[31:25], instruction[11:7]};  // store
      3'b011: immop = {{20{instruction[31]}}, instruction[7], instruction[30:25], instruction[11:8], 1
      'b0};  // branch
      3'b100: immop = {{12{instruction[31]}}, instruction[19:12], instruction[20], instruction[30:21], 1'b0}; // jump
      default: immop = 32'b0;
    endcase
  end

  // always_ff @(posedge clk) begin
  //   $display("immop: %h", immop);
  // end

endmodule

RISC-V-Single-Cycle/RTL/instrmem.sv
module instrmem #(
    parameter A_WIDTH = 32,
    D_WIDTH = 8
) (
    input [A_WIDTH-1:0] address,
    output [31:0] dout
);

  logic [D_WIDTH-1:0] rom_array[32'hBFC00FFF:32'hBFC00000]; 

  initial begin
    $display("Loading rom.");
    $readmemh("./programs/whole.hex", rom_array);
    $display("Program written to ROM successfully");
  end

  assign dout = {
    {rom_array[address]}, {rom_array[address+1]}, {rom_array[address+2]}, {rom_array[address+3]}
  };

endmodule

RISC-V-Single-Cycle/RTL/pcountunit.sv

module pcountunit #(
    parameter WIDTH = 32
) (
    input logic pcsrc, clk, rst, jbmux,
    input logic [WIDTH-1:0] jumpaddress,
    output logic [WIDTH-1:0] pc
);

  logic [WIDTH-1:0] next_pc;
  logic [WIDTH-1:0] branch_pc;

  initial begin
    assign branch_pc = 32'hBFC00000;
  end

  always_comb begin
    branch_pc = jbmux ? jumpaddress : pc + jumpaddress;
    next_pc   = pcsrc ? branch_pc : pc + 4;
  end

  always_ff @(posedge clk) begin
    if (rst) pc <= 32'hBFC00000;
    else pc <= next_pc;
  end



endmodule

RISC-V-Single-Cycle/RTL/controlunit.sv
module controlunit (
    input logic [6:0] opcode,
    input logic [2:0] funct3,
    input logic funct7, eq, 
    output logic regwrite, alusrc, pcsrc, memwrite, resultsrc, pcwritemux, jbmux, addupper,
    output logic [3:0] aluctrl,
    output logic [2:0] immsrc
);

  wire [1:0] aluop = {(opcode == 7'h33 | opcode == 7'h13 | opcode == 7'h37), (opcode == 7'h37 | opcode == 7'h63)};

  always_comb begin
    regwrite = opcode == 7'h13 | opcode == 7'h03 | opcode == 7'h33 | opcode >= 7'h67 | opcode == 7'h17 | opcode == 7'h37; 
    alusrc = opcode == 7'h03 | opcode == 7'h13 | opcode == 7'h23 | opcode == 7'h67 | opcode == 7'h17 | opcode == 7'h37; 
    memwrite = opcode == 7'h23;  
    resultsrc = opcode == 7'h03; 
    pcsrc = opcode >= 7'h67 | (opcode == 7'h63 & ((!eq & (funct3 == 3'h0 | funct3 == 3'h5 | funct3 == 3'h7)) | (eq & (funct3 == 3'h1 | funct3 == 3'h4 | funct3 == 3'h6)))); // pcsrc depends on eq implementation. funct3 must be integrated to distingush between each branch.
    jbmux = opcode == 7'h67; // selects which address pc should jump to
    pcwritemux = opcode >= 7'h67; // chooses between writing register with PC+4 or result from alu or load instruction
    addupper = opcode == 7'h17;
    case (opcode) 
      7'h13:   immsrc = 3'h0;  // imm
      7'h03:   immsrc = 3'h0;  // load
      7'h23:   immsrc = 3'h2;  // store
      7'h63:   immsrc = 3'h3;  // branch
      7'h33:   immsrc = 3'h7;  // reg
      7'h37:   immsrc = 3'h1;  // upp imm (load)
      7'h17:   immsrc = 3'h1;  // upp imm (add)
      default: immsrc = 3'h4;  // jump
    endcase
  end

  always_comb begin // aluctrl
    case (aluop)
      2'h0: aluctrl = 4'h0; // load and store and add upper
      2'h1: aluctrl = {1'h0, !funct3[2], funct3[2], funct3[1]}; // branch
      2'h2: aluctrl = {funct7 & ((opcode == 7'h13 & funct3 == 3'h5) | (opcode == 7'h33 & (funct3 == 3'h5 | funct3 == 3'h0))), funct3}; // reg or imm
      2'h3: aluctrl = 4'hf; //load upper
      default: aluctrl = 4'h9;
    endcase
  end
    
  // always_ff @(posedge clk) begin
  //   $display("eq: %h", eq, " regwrite: %h", regwrite, " aluctrl: %b", aluctrl, " alusrc: %h",
  //            alusrc, " pcsrc: %h", pcsrc, " aluop: %b", aluop, "\n");
  // end

endmodule

RISC-V-Single-Cycle/RTL/cpu.sv
module cpu #(
    parameter WIDTH = 32
) (
    input logic trigger, clk, rst,
    output logic [WIDTH-1:0] a0_output
);

  wire [WIDTH-1:0] rf_dout1, rf_dout2, interm_immop, prog_addr, interm_ins, interm_aluout, interm_loadout, interm_wdrf, jump_addr, interm_rfpc;
  wire [WIDTH-1:0] result = interm_resultsrc ? interm_loadout : interm_aluout;
  wire [6:0] interm_opcode;
  wire [3:0] interm_aluctrl;
  wire [2:0] interm_funct3, interm_immsrc;
  wire interm_funct7, interm_alusrc, interm_pcsrc, interm_eq, write_en, interm_memwrite, interm_resultsrc, interm_jbmux, interm_pcwritemux, interm_addupper;
  
  assign interm_opcode = interm_ins[6:0];
  assign interm_funct3 = interm_ins[14:12];
  assign interm_funct7 = interm_ins[30];
  assign interm_wdrf = interm_pcwritemux ? prog_addr + 4 : result;
  assign jump_addr = interm_jbmux ? result : interm_immop;
  assign interm_rfpc = interm_addupper ? prog_addr : rf_dout1;

  controlunit ctrlunit (
      .opcode(interm_opcode),
      .funct3(interm_funct3),
      .funct7(interm_funct7),
      .eq(interm_eq),  //in
      .regwrite(write_en),  //out
      .aluctrl(interm_aluctrl),  //out
      .alusrc(interm_alusrc),  //out
      .pcsrc(interm_pcsrc),  //out
      .immsrc(interm_immsrc),  //out
      .memwrite(interm_memwrite),  //out
      .resultsrc(interm_resultsrc),
      .jbmux(interm_jbmux),
      .pcwritemux(interm_pcwritemux),
      .addupper(interm_addupper)
  );

  pcountunit programcounter (
      .clk(clk),  //in
      .rst(rst),  //in
      .pcsrc(interm_pcsrc),  //in
      .jumpaddress(jump_addr),  //in
      .pc(prog_addr),  //out
      .jbmux(interm_jbmux)
  );

  instrmem programmem (
      .address(prog_addr),
      .dout(interm_ins)
  );

  signextender sgnextend (
      .instruction(interm_ins[31:7]),
      .immsrc(interm_immsrc),
      .immop(interm_immop)
  );

  alu alu (
      .alusrc(interm_alusrc),
      .aluctrl(interm_aluctrl),
      .aluop1(interm_rfpc),
      .immop(interm_immop),
      .regop2(rf_dout2),
      .aluout(interm_aluout),
      .eq(interm_eq)
  );

  rf registerfile (
      .clk(clk),  //in
      .we3(write_en),  //in
      .ad1(interm_ins[19:15]),  //in
      .ad2(interm_ins[24:20]),  //in
      .ad3(interm_ins[11:7]),  //in
      .wd3(interm_wdrf),  //in
      .a0(a0_output),  //out
      .rd1(rf_dout1),  //out
      .rd2(rf_dout2),  //out
      .trigger(trigger)
  );

  data_memory memory (
      .clk(clk),
      .write_enable(interm_memwrite),
      .addrmode(interm_funct3),
      .selectbytes(interm_aluout[1:0]),
      .write_data(rf_dout2),
      .address({interm_aluout[31:2], 2'b00}),
      .read_data(interm_loadout)
  );

  //   Display statement for whole and alu program
  //   always_ff @(posedge clk) begin
  //     $display("ins: %h", interm_ins, " progaddr: %h", prog_addr, "\n");
  //   end

endmodule

RISC-V-Single-Cycle/alu.vcd
$version Generated by VerilatedVcd $end
$date Tue Dec 13 19:29:47 2022
 $end
$timescale   1ps $end

 $scope module TOP $end
  $var wire 32 m a0_output [31:0] $end
  $var wire  1 k clk $end
  $var wire  1 l rst $end
  $var wire  1 j trigger $end
  $scope module cpu $end
   $var wire 32 n WIDTH [31:0] $end
   $var wire 32 m a0_output [31:0] $end
   $var wire  1 k clk $end
   $var wire  1 = interm_addupper $end
   $var wire  4 1 interm_aluctrl [3:0] $end
   $var wire 32 * interm_aluout [31:0] $end
   $var wire  1 5 interm_alusrc $end
   $var wire  1 7 interm_eq $end
   $var wire  3 2 interm_funct3 [2:0] $end
   $var wire  1 4 interm_funct7 $end
   $var wire 32 ' interm_immop [31:0] $end
   $var wire  3 3 interm_immsrc [2:0] $end
   $var wire 32 ) interm_ins [31:0] $end
   $var wire  1 ; interm_jbmux $end
   $var wire 32 + interm_loadout [31:0] $end
   $var wire  1 9 interm_memwrite $end
   $var wire  7 0 interm_opcode [6:0] $end
   $var wire  1 6 interm_pcsrc $end
   $var wire  1 < interm_pcwritemux $end
   $var wire  1 : interm_resultsrc $end
   $var wire 32 . interm_rfpc [31:0] $end
   $var wire 32 , interm_wdrf [31:0] $end
   $var wire 32 - jump_addr [31:0] $end
   $var wire 32 ( prog_addr [31:0] $end
   $var wire 32 / result [31:0] $end
   $var wire 32 % rf_dout1 [31:0] $end
   $var wire 32 & rf_dout2 [31:0] $end
   $var wire  1 l rst $end
   $var wire  1 j trigger $end
   $var wire  1 8 write_en $end
   $scope module alu $end
    $var wire 32 n D_WIDTH [31:0] $end
    $var wire  4 1 aluctrl [3:0] $end
    $var wire 32 . aluop1 [31:0] $end
    $var wire 32 B aluop2 [31:0] $end
    $var wire 32 * aluout [31:0] $end
    $var wire  1 5 alusrc $end
    $var wire  1 7 eq $end
    $var wire 32 ' immop [31:0] $end
    $var wire 32 & regop2 [31:0] $end
   $upscope $end
   $scope module ctrlunit $end
    $var wire  1 = addupper $end
    $var wire  4 1 aluctrl [3:0] $end
    $var wire  2 > aluop [1:0] $end
    $var wire  1 5 alusrc $end
    $var wire  1 7 eq $end
    $var wire  3 2 funct3 [2:0] $end
    $var wire  1 4 funct7 $end
    $var wire  3 3 immsrc [2:0] $end
    $var wire  1 ; jbmux $end
    $var wire  1 9 memwrite $end
    $var wire  7 0 opcode [6:0] $end
    $var wire  1 6 pcsrc $end
    $var wire  1 < pcwritemux $end
    $var wire  1 8 regwrite $end
    $var wire  1 : resultsrc $end
   $upscope $end
   $scope module memory $end
    $var wire 32 n ADDRESS_WIDTH [31:0] $end
    $var wire 32 n DATA_WIDTH [31:0] $end
    $var wire 32 g address [31:0] $end
    $var wire  3 2 addrmode [2:0] $end
    $var wire  1 k clk $end
    $var wire 32 i ramin [31:0] $end
    $var wire 32 h ramout [31:0] $end
    $var wire 32 + read_data [31:0] $end
    $var wire  2 f selectbytes [1:0] $end
    $var wire 32 & write_data [31:0] $end
    $var wire  1 9 write_enable $end
    $scope module loadmem $end
     $var wire 32 n D_WIDTH [31:0] $end
     $var wire  3 2 addrmode [2:0] $end
     $var wire 32 h ramout [31:0] $end
     $var wire 32 + read_data [31:0] $end
     $var wire  2 f selectbytes [1:0] $end
    $upscope $end
    $scope module ram $end
     $var wire 32 n ADDRESS_WIDTH [31:0] $end
     $var wire 32 o DATA_WIDTH [31:0] $end
     $var wire 32 g address [31:0] $end
     $var wire  1 k clk $end
     $var wire 32 i ramin [31:0] $end
     $var wire 32 h ramout [31:0] $end
     $var wire  1 9 write_enable $end
     $scope module unnamedblk1 $end
      $var wire 32 $ i [31:0] $end
     $upscope $end
    $upscope $end
    $scope module storemem $end
     $var wire 32 n DATA_WIDTH [31:0] $end
     $var wire  3 2 addrmode [2:0] $end
     $var wire 32 i ramdin [31:0] $end
     $var wire 32 h ramout [31:0] $end
     $var wire  2 f selectbytes [1:0] $end
     $var wire 32 & write_data [31:0] $end
    $upscope $end
   $upscope $end
   $scope module programcounter $end
    $var wire 32 n WIDTH [31:0] $end
    $var wire 32 @ branch_pc [31:0] $end
    $var wire  1 k clk $end
    $var wire  1 ; jbmux $end
    $var wire 32 - jumpaddress [31:0] $end
    $var wire 32 ? next_pc [31:0] $end
    $var wire 32 ( pc [31:0] $end
    $var wire  1 6 pcsrc $end
    $var wire  1 l rst $end
   $upscope $end
   $scope module programmem $end
    $var wire 32 n A_WIDTH [31:0] $end
    $var wire 32 o D_WIDTH [31:0] $end
    $var wire 32 ( address [31:0] $end
    $var wire 32 ) dout [31:0] $end
   $upscope $end
   $scope module registerfile $end
    $var wire 32 p A_WIDTH [31:0] $end
    $var wire 32 n D_WIDTH [31:0] $end
    $var wire 32 m a0 [31:0] $end
    $var wire  5 C ad1 [4:0] $end
    $var wire  5 D ad2 [4:0] $end
    $var wire  5 E ad3 [4:0] $end
    $var wire  1 k clk $end
    $var wire 32 % rd1 [31:0] $end
    $var wire 32 & rd2 [31:0] $end
    $var wire 32 F rf_array(0) [31:0] $end
    $var wire 32 G rf_array(1) [31:0] $end
    $var wire 32 P rf_array(10) [31:0] $end
    $var wire 32 Q rf_array(11) [31:0] $end
    $var wire 32 R rf_array(12) [31:0] $end
    $var wire 32 S rf_array(13) [31:0] $end
    $var wire 32 T rf_array(14) [31:0] $end
    $var wire 32 U rf_array(15) [31:0] $end
    $var wire 32 V rf_array(16) [31:0] $end
    $var wire 32 W rf_array(17) [31:0] $end
    $var wire 32 X rf_array(18) [31:0] $end
    $var wire 32 Y rf_array(19) [31:0] $end
    $var wire 32 H rf_array(2) [31:0] $end
    $var wire 32 Z rf_array(20) [31:0] $end
    $var wire 32 [ rf_array(21) [31:0] $end
    $var wire 32 \ rf_array(22) [31:0] $end
    $var wire 32 ] rf_array(23) [31:0] $end
    $var wire 32 ^ rf_array(24) [31:0] $end
    $var wire 32 _ rf_array(25) [31:0] $end
    $var wire 32 ` rf_array(26) [31:0] $end
    $var wire 32 a rf_array(27) [31:0] $end
    $var wire 32 b rf_array(28) [31:0] $end
    $var wire 32 c rf_array(29) [31:0] $end
    $var wire 32 I rf_array(3) [31:0] $end
    $var wire 32 d rf_array(30) [31:0] $end
    $var wire 32 e rf_array(31) [31:0] $end
    $var wire 32 J rf_array(4) [31:0] $end
    $var wire 32 K rf_array(5) [31:0] $end
    $var wire 32 L rf_array(6) [31:0] $end
    $var wire 32 M rf_array(7) [31:0] $end
    $var wire 32 N rf_array(8) [31:0] $end
    $var wire 32 O rf_array(9) [31:0] $end
    $var wire  1 j trigger $end
    $var wire 32 , wd3 [31:0] $end
    $var wire  1 8 we3 $end
    $scope module unnamedblk1 $end
     $var wire 32 # i [31:0] $end
    $upscope $end
   $upscope $end
   $scope module sgnextend $end
    $var wire 32 ' immop [31:0] $end
    $var wire  3 3 immsrc [2:0] $end
    $var wire 25 A instruction [31:7] $end
   $upscope $end
  $upscope $end
 $upscope $end
$enddefinitions $end


#0
b00000000000000000000000000000000 #
b00000000000000000000000000000000 $
b00000000000000000000000000000000 %
b00000000000000000000000000000000 &
b00000000000000000000000000000000 '
b00000000000000000000000000000000 (
b00000000000000000000000000000000 )
b00000000000000000000000000000000 *
b00000000000000000000000000000000 +
b00000000000000000000000000000000 ,
b00000000000000000000000000000000 -
b00000000000000000000000000000000 .
b00000000000000000000000000000000 /
b0000000 0
b0000 1
b000 2
b000 3
04
05
06
07
08
09
0:
0;
0<
0=
b00 >
b00000000000000000000000000000000 ?
b00000000000000000000000000000000 @
b0000000000000000000000000 A
b00000000000000000000000000000000 B
b00000 C
b00000 D
b00000 E
b00000000000000000000000000000000 F
b00000000000000000000000000000000 G
b00000000000000000000000000000000 H
b00000000000000000000000000000000 I
b00000000000000000000000000000000 J
b00000000000000000000000000000000 K
b00000000000000000000000000000000 L
b00000000000000000000000000000000 M
b00000000000000000000000000000000 N
b00000000000000000000000000000000 O
b00000000000000000000000000000000 P
b00000000000000000000000000000000 Q
b00000000000000000000000000000000 R
b00000000000000000000000000000000 S
b00000000000000000000000000000000 T
b00000000000000000000000000000000 U
b00000000000000000000000000000000 V
b00000000000000000000000000000000 W
b00000000000000000000000000000000 X
b00000000000000000000000000000000 Y
b00000000000000000000000000000000 Z
b00000000000000000000000000000000 [
b00000000000000000000000000000000 \
b00000000000000000000000000000000 ]
b00000000000000000000000000000000 ^
b00000000000000000000000000000000 _
b00000000000000000000000000000000 `
b00000000000000000000000000000000 a
b00000000000000000000000000000000 b
b00000000000000000000000000000000 c
b00000000000000000000000000000000 d
b00000000000000000000000000000000 e
b00 f
b00000000000000000000000000000000 g
b00000000000000000000000000000000 h
b00000000000000000000000000000000 i
0j
0k
0l
b00000000000000000000000000000000 m
b00000000000000000000000000100000 n
b00000000000000000000000000001000 o
b00000000000000000000000000000101 p
#1
b00000000000000000000000000100000 #
b00000000000000100000000000000000 $
b00011110111000010000000000000000 '
b00011110111000010000010100110111 )
b00011110111000010000000000000000 *
b00011110111000010000000000000000 ,
b00011110111000010000000000000000 -
b00011110111000010000000000000000 /
b0110111 0
b1111 1
b001 3
15
18
b11 >
b00000000000000000000000000000100 ?
b00011110111000010000000000000000 @
b0001111011100001000001010 A
b00011110111000010000000000000000 B
b00010 C
b01110 D
b01010 E
b00011110111000010000000000000000 g
1k
#2
0k
#3
b00000000000000000000000000000000 '
b00000000000000000000000000000100 (
b00000000000000000000000000010011 )
b00000000000000000000000000000000 *
b00000000000000000000000000000000 ,
b00000000000000000000000000000000 -
b00000000000000000000000000000000 /
b0010011 0
b0000 1
b000 3
b10 >
b00000000000000000000000000001000 ?
b00000000000000000000000000000100 @
b0000000000000000000000000 A
b00000000000000000000000000000000 B
b00000 C
b00000 D
b00000 E
b00011110111000010000000000000000 P
b00000000000000000000000000000000 g
1k
b00011110111000010000000000000000 m
#4
0k
#5
b00000000000000000000000000001000 (
b00000000000000000000000000001100 ?
b00000000000000000000000000001000 @
1k
#6
0k
#7
b00011110111000010000000000000000 %
b00000000000000000000010000010000 '
b00000000000000000000000000001100 (
b01000001000001010101010100010011 )
b00000000000000000001111011100001 *
b00000000000000000001111011100001 ,
b00000000000000000000010000010000 -
b00011110111000010000000000000000 .
b00000000000000000001111011100001 /
b1101 1
b101 2
14
17
b00000000000000000000000000010000 ?
b00000000000000000000010000011100 @
b0100000100000101010101010 A
b00000000000000000000010000010000 B
b01010 C
b10000 D
b01010 E
b01 f
b00000000000000000001111011100000 g
1k
#8
0k
#9
b00000000000000000000000000000000 %
b00000000000000000000000000000001 '
b00000000000000000000000000010000 (
b00000000000100000000001010010011 )
b00000000000000000000000000000001 *
b00000000000000000000000000000001 ,
b00000000000000000000000000000001 -
b00000000000000000000000000000000 .
b00000000000000000000000000000001 /
b0000 1
b000 2
04
b00000000000000000000000000010100 ?
b00000000000000000000000000010001 @
b0000000000010000000000101 A
b00000000000000000000000000000001 B
b00000 C
b00001 D
b00101 E
b00000000000000000001111011100001 P
b00000000000000000000000000000000 g
1k
b00000000000000000001111011100001 m
#10
0k
#11
b00000000000000000001111011100001 %
b00000000000000000000000000010000 '
b00000000000000000000000000010100 (
b00000001000001010000101010010011 )
b00000000000000000001111011110001 *
b00000000000000000001111011110001 ,
b00000000000000000000000000010000 -
b00000000000000000001111011100001 .
b00000000000000000001111011110001 /
b00000000000000000000000000011000 ?
b00000000000000000000000000100100 @
b0000000100000101000010101 A
b00000000000000000000000000010000 B
b01010 C
b10000 D
b10101 E
b00000000000000000000000000000001 K
b00000000000000000001111011110000 g
1k
#12
0k
#13
b00000000000000000001111011110001 %
b00000000000000000000000000000001 &
b00000000000000000000000000000000 '
b00000000000000000000000000011000 (
b01000000010110101000101100110011 )
b00000000000000000001111011110000 *
b00000000000000000001111011110000 ,
b00000000000000000000000000000000 -
b00000000000000000001111011110001 .
b00000000000000000001111011110000 /
b0110011 0
b1000 1
b111 3
14
05
07
b00000000000000000000000000011100 ?
b00000000000000000000000000011000 @
b0100000001011010100010110 A
b00000000000000000000000000000001 B
b10101 C
b00101 D
b10110 E
b00000000000000000001111011110001 [
b00 f
b00000000000000000000000000000001 i
1k
#14
0k
#15
b00000000000000000001111011110000 %
b00000000000000000000000000000000 &
b00000000000000000000000000011000 '
b00000000000000000000000000011100 (
b00000001100010110001101110010011 )
b11110000000000000000000000000000 *
b11110000000000000000000000000000 ,
b00000000000000000000000000011000 -
b00000000000000000001111011110000 .
b11110000000000000000000000000000 /
b0010011 0
b0001 1
b001 2
b000 3
04
15
b00000000000000000000000000100000 ?
b00000000000000000000000000110100 @
b0000000110001011000110111 A
b00000000000000000000000000011000 B
b10110 C
b11000 D
b10111 E
b00000000000000000001111011110000 \
b11110000000000000000000000000000 g
b00000000000000000000000000000000 i
1k
#16
0k
#17
b11110000000000000000000000000000 %
b00000000000000000000010000000100 '
b00000000000000000000000000100000 (
b01000000010010111101010100010011 )
b11111111000000000000000000000000 *
b11111111000000000000000000000000 ,
b00000000000000000000010000000100 -
b11110000000000000000000000000000 .
b11111111000000000000000000000000 /
b1101 1
b101 2
14
b00000000000000000000000000100100 ?
b00000000000000000000010000100100 @
b0100000001001011110101010 A
b00000000000000000000010000000100 B
b10111 C
b00100 D
b01010 E
b11110000000000000000000000000000 ]
b11111111000000000000000000000000 g
1k
#18
0k
#19
b11111111000000000000000000000000 %
b00000000000000000000000000000100 '
b00000000000000000000000000100100 (
b00000000010001010101010110010011 )
b00001111111100000000000000000000 *
b00001111111100000000000000000000 ,
b00000000000000000000000000000100 -
b11111111000000000000000000000000 .
b00001111111100000000000000000000 /
b0101 1
04
b00000000000000000000000000101000 ?
b00000000000000000000000000101000 @
b0000000001000101010101011 A
b00000000000000000000000000000100 B
b01010 C
b01011 E
b11111111000000000000000000000000 P
b00001111111100000000000000000000 g
1k
b11111111000000000000000000000000 m
#20
0k
#21
b00000000000000000001111011110001 %
b00000000000000000000000000000001 '
b00000000000000000000000000101000 (
b00000000000110101111011000010011 )
b00000000000000000000000000000001 *
b00000000000000000000000000000001 ,
b00000000000000000000000000000001 -
b00000000000000000001111011110001 .
b00000000000000000000000000000001 /
b0111 1
b111 2
17
b00000000000000000000000000101100 ?
b00000000000000000000000000101001 @
b0000000000011010111101100 A
b00000000000000000000000000000001 B
b10101 C
b00001 D
b01100 E
b00001111111100000000000000000000 Q
b01 f
b00000000000000000000000000000000 g
1k
#22
0k
