RISC-V-Base-CPU/ram.sv
module ram #(
    parameter A_WIDTH = 32,
    D_WIDTH = 8
) (
    input logic [A_WIDTH-1:0] address, wd,
    input logic [2:0] bytes,
    input logic clk, we,
    output logic [31:0] dout
);

  logic [D_WIDTH-1:0] ram_array[200000:0];

  initial begin
    for (int i = 0; i < $size(ram_array); i++) begin
      ram_array[i] = 8'b0;
    end
  end

  //read
  always_comb begin
    case (bytes)
      3'b000: dout = {{5'd24{ram_array[address][7]}}, {ram_array[address]}};  //load byte   
      3'b001:
      dout = {
        {5'd16{ram_array[address+1][7]}}, {ram_array[address+1]}, {ram_array[address]}
      };  //load half
      3'b010:
      dout = {
        {ram_array[address+3]}, {ram_array[address+2]}, {ram_array[address+1]}, {ram_array[address]}
      };  //load word
      3'b100: dout = {{24'b0}, {ram_array[address]}};  //load byte uns
      3'b101: dout = {{16'b0}, {ram_array[address+1]}, {ram_array[address]}};  //load half uns
      default: begin
        dout = 32'b0;
      end
    endcase
  end

  //write
  always_ff @(posedge clk) begin
    // $display("[0]: ", ram_array[0], " [5]: ", ram_array[5], " [4]: ", ram_array[4], " [8]:", ram_array[8], " dout lb: ", dout , "\n");
    if (we) begin
      case (bytes)
        3'b000: ram_array[address] <= wd[7:0];  //str byte

        3'b001: begin
          ram_array[address]   <= wd[7:0];  //str half
          ram_array[address+1] <= wd[15:8];
        end

        3'b010: begin  //str word
          ram_array[address]   <= wd[7:0];
          ram_array[address+1] <= wd[15:8];
          ram_array[address+2] <= wd[23:16];
          ram_array[address+3] <= wd[31:24];
        end
        default: begin
          ram_array[address] <= ram_array[address];
        end
      endcase
    end
  end

endmodule

RISC-V-Base-CPU/rf.sv
module rf #(
    parameter  A_WIDTH = 5,
                D_WIDTH = 32
) (
    input logic clk, we3,
    input logic [A_WIDTH-1:0] ad1, ad2, ad3, wd3,
    output logic [D_WIDTH-1:0] a0, rd1, rd2
);

    logic [D_WIDTH-1:0] rf_array [2**A_WIDTH-1:0];

    always_comb begin
        rd1 = rf_array[ad1];
        rd2 = rf_array[ad2];
    end

    initial begin
        for (int i = 0; i < $size(rf_array); i++) begin
            rf_array[i] = 32'h0000;
        end
    end

    assign a0 = rf_array[10];


    always_ff @(posedge clk) begin
        // $display("a0:", a0 , " a1: ", rf_array[11], " a2: ", rf_array[12], " din: ", wd3);
        if(we3) rf_array[ad3] <= wd3; 
    end
    
    
    
endmodule

RISC-V-Base-CPU/alu.sv
module alu #(
    parameter D_WIDTH = 32
) (
    input logic alusrc,
    input logic [2:0] aluctrl,
    input logic [D_WIDTH-1:0] aluop1, immop, regop2,
    output logic [D_WIDTH-1:0] aluout,
    output logic eq
);

  logic [D_WIDTH-1:0] aluop2;
  assign aluop2 = alusrc ? immop : regop2;
  always_comb begin

    case (aluctrl)
      3'b000:  aluout = aluop1 + aluop2;
      3'b001:  aluout = aluop1 - aluop2;
      3'b010:  aluout = aluop1 & aluop2;
      3'b011:  aluout = aluop1 | aluop2;
      3'b100:  aluout = 32'b0;
      3'b101:  aluout = 32'hffff;  //slt
      3'b110:  aluout = 32'b0;
      3'b111:  aluout = 32'b0;
      default: aluout = 0;
    endcase
  end


  assign eq = (aluop1 == aluop2);


endmodule

RISC-V-Base-CPU/signextender.sv
module signextender (
    input  logic [31:0] instruction,
    input  logic [ 2:0] immsrc,
    output logic [31:0] immop
);

  always_comb begin
    case (immsrc)
      3'b000: immop = {{5'd20{instruction[31]}}, instruction[31:20]};  // immediate
      3'b001: immop = {{5'd12{instruction[31]}}, instruction[31:12]};  // upper immediate
      3'b010: immop = {{5'd20{instruction[31]}}, instruction[31:25], instruction[11:7]};  // store
      3'b011:
      immop = {
        {5'd21{instruction[31]}}, instruction[7], instruction[30:25], instruction[11:8]
      };  // branch
      // 3'b100: immop = {instruction[31], instruction[19:12], instruction[20], instruction[30:21]}; // jump
      default: immop = 32'b0;
    endcase
  end

endmodule

RISC-V-Base-CPU/instrmem.sv
module instrmem #(
    parameter A_WIDTH = 32,
    D_WIDTH = 8
) (
    input [A_WIDTH-1:0] address,
    output [31:0] dout
);
  logic [D_WIDTH-1:0] rom_array [2000:0];

  initial begin
    $display("Loading rom.");
    $readmemh("counter.hex", rom_array);
    $display("Program written to ROM successfully");
  end

  assign dout = {
    {rom_array[address]}, {rom_array[address+1]}, {rom_array[address+2]}, {rom_array[address+3]}
  };

endmodule

RISC-V-Base-CPU/pcountunit.sv

module pcountunit #(
    parameter WIDTH = 32
) (
    input logic pcsrc, clk, rst,
    input logic [WIDTH-1:0] immop,
    output logic [WIDTH-1:0] pc
);

  logic [WIDTH-1:0] next_pc;
  logic [WIDTH-1:0] branch_pc;

  always_comb begin
    branch_pc = pc + immop;
    next_pc   = pcsrc ? branch_pc : pc + 4;
  end

  always_ff @(posedge clk) begin
    if (rst) pc <= 32'b0;
    else pc <= next_pc;
  end



endmodule

RISC-V-Base-CPU/controlunit.sv
module controlunit (
    input logic [31:0] instruction,
    input logic eq,
    output logic regwrite, alusrc, pcsrc, memwrite, resultsrc,
    output logic [2:0] aluctrl, immsrc, addrmode
);

  
endmodule

RISC-V-Base-CPU/cpu.sv
module cpu #(
    parameter WIDTH = 32
) (
    input logic clk, rst,
    output logic [4:0] rd_add,
    output logic [WIDTH-1:0] prog_addr, interm_ins, rout_test, a0_output, rf_dout1, rf_dout2, interm_immop
);

  wire [WIDTH-1:0] interm_aluout, result = interm_resultsrc ? rout_test : interm_aluout;
  wire [2:0] interm_aluctrl, interm_immsrc, inter_addrmode;
  wire interm_memwrite, interm_resultsrc, write_en, interm_pcsrc, interm_eq, interm_alusrc;
  
  assign rd_add = interm_ins[19:15];

  controlunit ctrlunit (
      .instruction(interm_ins),  //in
      .eq(interm_eq),  //in
      .regwrite(write_en),  //out
      .aluctrl(interm_aluctrl),  //out
      .alusrc(interm_alusrc),  //out
      .pcsrc(interm_pcsrc),  //out
      .immsrc(interm_immsrc),  //out
      .memwrite(interm_memwrite),  //out
      .addrmode(inter_addrmode),  //out
      .resultsrc(interm_resultsrc)  //out
  );

  pcountunit programcounter (
      .clk(clk),  //in
      .rst(rst),  //in
      .pcsrc(interm_pcsrc),  //in
      .immop(interm_immop),  //in
      .pc(prog_addr)  //out
  );

  instrmem programmem (
      .address(prog_addr),
      .dout(interm_ins)
  );

  signextender sgnextend (
      .instruction(interm_ins),
      .immsrc(interm_immsrc),
      .immop(interm_immop)
  );


  alu alu (
      .alusrc(interm_alusrc),
      .aluctrl(interm_aluctrl),
      .aluop1(rf_dout1),
      .immop(interm_immop),
      .regop2(rf_dout2),
      .aluout(interm_aluout),
      .eq(interm_eq)
  );

  rf registerfile (
      .clk(clk),  //in
      .we3(write_en),  //in
      .ad1(interm_ins[19:15]),  //in
      .ad2(interm_ins[24:20]),  //in
      .ad3(interm_ins[11:7]),  //in
      .wd3(result),  //in
      .a0(a0_output),  //out
      .rd1(rf_dout1),  //out
      .rd2(rf_dout2)  //out
  );

  ram ram (
      .clk(clk),
      .address(interm_aluout),
      .bytes(inter_addrmode),
      .we(interm_memwrite),
      .wd(rf_dout2),
      .dout(rout_test)
  );



endmodule

RISC-V-Base-CPU/cpu.vcd
$version Generated by VerilatedVcd $end
$date Fri Dec  2 16:31:57 2022 $end
$timescale 1ps $end

 $scope module TOP $end
  $var wire 32 P a0_output [31:0] $end
  $var wire  1 J clk $end
  $var wire 32 S interm_immop [31:0] $end
  $var wire 32 N interm_ins [31:0] $end
  $var wire 32 M prog_addr [31:0] $end
  $var wire  5 L rd_add [4:0] $end
  $var wire 32 Q rf_dout1 [31:0] $end
  $var wire 32 R rf_dout2 [31:0] $end
  $var wire 32 O rout_test [31:0] $end
  $var wire  1 K rst $end
  $scope module cpu $end
   $var wire 32 X WIDTH [31:0] $end
   $var wire 32 P a0_output [31:0] $end
   $var wire  1 J clk $end
   $var wire  3 [ inter_addrmode [2:0] $end
   $var wire  3 Y interm_aluctrl [2:0] $end
   $var wire 32 % interm_aluout [31:0] $end
   $var wire  1 ` interm_alusrc $end
   $var wire  1 U interm_eq $end
   $var wire 32 S interm_immop [31:0] $end
   $var wire  3 Z interm_immsrc [2:0] $end
   $var wire 32 N interm_ins [31:0] $end
   $var wire  1 \ interm_memwrite $end
   $var wire  1 _ interm_pcsrc $end
   $var wire  1 ] interm_resultsrc $end
   $var wire 32 M prog_addr [31:0] $end
   $var wire  5 L rd_add [4:0] $end
   $var wire 32 T result [31:0] $end
   $var wire 32 Q rf_dout1 [31:0] $end
   $var wire 32 R rf_dout2 [31:0] $end
   $var wire 32 O rout_test [31:0] $end
   $var wire  1 K rst $end
   $var wire  1 ^ write_en $end
   $scope module alu $end
    $var wire 32 X D_WIDTH [31:0] $end
    $var wire  3 Y aluctrl [2:0] $end
    $var wire 32 Q aluop1 [31:0] $end
    $var wire 32 & aluop2 [31:0] $end
    $var wire 32 % aluout [31:0] $end
    $var wire  1 ` alusrc $end
    $var wire  1 U eq $end
    $var wire 32 S immop [31:0] $end
    $var wire 32 R regop2 [31:0] $end
   $upscope $end
   $scope module ctrlunit $end
    $var wire  3 [ addrmode [2:0] $end
    $var wire  3 Y aluctrl [2:0] $end
    $var wire  1 ` alusrc $end
    $var wire  1 U eq $end
    $var wire  3 Z immsrc [2:0] $end
    $var wire 32 N instruction [31:0] $end
    $var wire  1 \ memwrite $end
    $var wire  1 _ pcsrc $end
    $var wire  1 ^ regwrite $end
    $var wire  1 ] resultsrc $end
   $upscope $end
   $scope module programcounter $end
    $var wire 32 X WIDTH [31:0] $end
    $var wire 32 ( branch_pc [31:0] $end
    $var wire  1 J clk $end
    $var wire 32 S immop [31:0] $end
    $var wire 32 ' next_pc [31:0] $end
    $var wire 32 M pc [31:0] $end
    $var wire  1 _ pcsrc $end
    $var wire  1 K rst $end
   $upscope $end
   $scope module programmem $end
    $var wire 32 X A_WIDTH [31:0] $end
    $var wire 32 a D_WIDTH [31:0] $end
    $var wire 32 M address [31:0] $end
    $var wire 32 N dout [31:0] $end
   $upscope $end
   $scope module ram $end
    $var wire 32 X A_WIDTH [31:0] $end
    $var wire 32 a D_WIDTH [31:0] $end
    $var wire 32 % address [31:0] $end
    $var wire  3 [ bytes [2:0] $end
    $var wire  1 J clk $end
    $var wire 32 O dout [31:0] $end
    $var wire 32 R wd [31:0] $end
    $var wire  1 \ we $end
    $scope module unnamedblk1 $end
     $var wire 32 # i [31:0] $end
    $upscope $end
   $upscope $end
   $scope module registerfile $end
    $var wire 32 b A_WIDTH [31:0] $end
    $var wire 32 X D_WIDTH [31:0] $end
    $var wire 32 P a0 [31:0] $end
    $var wire  5 L ad1 [4:0] $end
    $var wire  5 V ad2 [4:0] $end
    $var wire  5 ) ad3 [4:0] $end
    $var wire  1 J clk $end
    $var wire 32 Q rd1 [31:0] $end
    $var wire 32 R rd2 [31:0] $end
    $var wire 32 * rf_array[0] [31:0] $end
    $var wire 32 4 rf_array[10] [31:0] $end
    $var wire 32 5 rf_array[11] [31:0] $end
    $var wire 32 6 rf_array[12] [31:0] $end
    $var wire 32 7 rf_array[13] [31:0] $end
    $var wire 32 8 rf_array[14] [31:0] $end
    $var wire 32 9 rf_array[15] [31:0] $end
    $var wire 32 : rf_array[16] [31:0] $end
    $var wire 32 ; rf_array[17] [31:0] $end
    $var wire 32 < rf_array[18] [31:0] $end
    $var wire 32 = rf_array[19] [31:0] $end
    $var wire 32 + rf_array[1] [31:0] $end
    $var wire 32 > rf_array[20] [31:0] $end
    $var wire 32 ? rf_array[21] [31:0] $end
    $var wire 32 @ rf_array[22] [31:0] $end
    $var wire 32 A rf_array[23] [31:0] $end
    $var wire 32 B rf_array[24] [31:0] $end
    $var wire 32 C rf_array[25] [31:0] $end
    $var wire 32 D rf_array[26] [31:0] $end
    $var wire 32 E rf_array[27] [31:0] $end
    $var wire 32 F rf_array[28] [31:0] $end
    $var wire 32 G rf_array[29] [31:0] $end
    $var wire 32 , rf_array[2] [31:0] $end
    $var wire 32 H rf_array[30] [31:0] $end
    $var wire 32 I rf_array[31] [31:0] $end
    $var wire 32 - rf_array[3] [31:0] $end
    $var wire 32 . rf_array[4] [31:0] $end
    $var wire 32 / rf_array[5] [31:0] $end
    $var wire 32 0 rf_array[6] [31:0] $end
    $var wire 32 1 rf_array[7] [31:0] $end
    $var wire 32 2 rf_array[8] [31:0] $end
    $var wire 32 3 rf_array[9] [31:0] $end
    $var wire  5 W wd3 [4:0] $end
    $var wire  1 ^ we3 $end
    $scope module unnamedblk1 $end
     $var wire 32 $ i [31:0] $end
    $upscope $end
   $upscope $end
   $scope module sgnextend $end
    $var wire 32 S immop [31:0] $end
    $var wire  3 Z immsrc [2:0] $end
    $var wire 32 N instruction [31:0] $end
   $upscope $end
  $upscope $end
 $upscope $end
$enddefinitions $end


#0
b00000000000000000000000000000000 #
b00000000000000000000000000000000 $
b00000000000000000000000000000000 %
b00000000000000000000000000000000 &
b00000000000000000000000000000000 '
b00000000000000000000000000000000 (
b00000 )
b00000000000000000000000000000000 *
b00000000000000000000000000000000 +
b00000000000000000000000000000000 ,
b00000000000000000000000000000000 -
b00000000000000000000000000000000 .
b00000000000000000000000000000000 /
b00000000000000000000000000000000 0
b00000000000000000000000000000000 1
b00000000000000000000000000000000 2
b00000000000000000000000000000000 3
b00000000000000000000000000000000 4
b00000000000000000000000000000000 5
b00000000000000000000000000000000 6
b00000000000000000000000000000000 7
b00000000000000000000000000000000 8
b00000000000000000000000000000000 9
b00000000000000000000000000000000 :
b00000000000000000000000000000000 ;
b00000000000000000000000000000000 <
b00000000000000000000000000000000 =
b00000000000000000000000000000000 >
b00000000000000000000000000000000 ?
b00000000000000000000000000000000 @
b00000000000000000000000000000000 A
b00000000000000000000000000000000 B
b00000000000000000000000000000000 C
b00000000000000000000000000000000 D
b00000000000000000000000000000000 E
b00000000000000000000000000000000 F
b00000000000000000000000000000000 G
b00000000000000000000000000000000 H
b00000000000000000000000000000000 I
0J
0K
b00000 L
b00000000000000000000000000000000 M
b00000000000000000000000000000000 N
b00000000000000000000000000000000 O
b00000000000000000000000000000000 P
b00000000000000000000000000000000 Q
b00000000000000000000000000000000 R
b00000000000000000000000000000000 S
b00000000000000000000000000000000 T
1U
b00000 V
b00000 W
b00000000000000000000000000100000 X
b000 Y
b000 Z
b000 [
0\
0]
0^
0_
0`
b00000000000000000000000000001000 a
b00000000000000000000000000000101 b
#1
b00000000000000110000110101000001 #
b00000000000000000000000000100000 $
b00000000000000000000000000000100 '
b00000000000000000000000011111111 (
b00110 )
1J
b00001111111100000000001100010011 N
b00000000000000000000000011111111 S
b11111 V
#2
0J
#3
b00000000000000000000000000001000 '
b00000000000000000000000000000100 (
b01010 )
1J
b00000000000000000000000000000100 M
b00000000000000000000010100010011 N
b00000000000000000000000000000000 S
b00000 V
#4
0J
#5
b00000000000000000000000000001100 '
b00000000000000000000000011111000 (
b01011 )
1J
b00000000000000000000000000001000 M
b00001111000000000000010110010011 N
b00000000000000000000000011110000 S
b10000 V
#6
0J
#7
b00000000000000000000000000010000 '
b00000000000000000000000000001100 (
b01010 )
1J
b01011 L
b00000000000000000000000000001100 M
b00000000000001011000010100010011 N
b00000000000000000000000000000000 S
b00000 V
#8
0J
#9
b00000000000000000000000000010100 '
b00000000000000000000000000010001 (
b01011 )
1J
b00000000000000000000000000010000 M
b00000000000101011000010110010011 N
b00000000000000000000000000000001 S
b00001 V
#10
0J
#11
b00000000000000000000000000011000 '
b11111111111111111111111111111010 (
b10001 )
1J
b00000000000000000000000000010100 M
b11111110011001011001100011100011 N
b11111111111111111111111111100110 S
b00110 V
#12
0J
#13
b00000000000000000000000000011100 '
b11111111111111111111111111111000 (
b00001 )
1J
b00110 L
b00000000000000000000000000011000 M
b11111110000000110001000011100011 N
b11111111111111111111111111100000 S
b00000 V
#14
0J
#15
b00000000000000000000000000100000 '
b00000000000000000000000000011100 (
b00000 )
1J
b00000 L
b00000000000000000000000000011100 M
b00000000000000000000000000000000 N
b00000000000000000000000000000000 S
#16
0J
#17
b00000000000000000000000000100100 '
b00000000000000000000000000100000 (
1J
b00000000000000000000000000100000 M
#18
0J
#19
b00000000000000000000000000101000 '
b00000000000000000000000000100100 (
1J
b00000000000000000000000000100100 M
#20
0J
#21
b00000000000000000000000000101100 '
b00000000000000000000000000101000 (
1J
b00000000000000000000000000101000 M
#22
0J
#23
b00000000000000000000000000110000 '
b00000000000000000000000000101100 (
1J
b00000000000000000000000000101100 M
#24
0J
#25
b00000000000000000000000000110100 '
b00000000000000000000000000110000 (
1J
b00000000000000000000000000110000 M
#26
0J
#27
b00000000000000000000000000111000 '
b00000000000000000000000000110100 (
1J
b00000000000000000000000000110100 M
#28
0J
#29
b00000000000000000000000000111100 '
b00000000000000000000000000111000 (
1J
b00000000000000000000000000111000 M
#30
0J
#31
b00000000000000000000000001000000 '
b00000000000000000000000000111100 (
1J
b00000000000000000000000000111100 M
#32
0J
#33
b00000000000000000000000001000100 '
b00000000000000000000000001000000 (
1J
b00000000000000000000000001000000 M
#34
0J
#35
b00000000000000000000000001001000 '
b00000000000000000000000001000100 (
1J
b00000000000000000000000001000100 M
#36
0J
#37
b00000000000000000000000001001100 '
b00000000000000000000000001001000 (
1J
b00000000000000000000000001001000 M
#38
0J
#39
b00000000000000000000000001010000 '
b00000000000000000000000001001100 (
1J
b00000000000000000000000001001100 M
#40
0J
#41
b00000000000000000000000001010100 '
b00000000000000000000000001010000 (
1J
b00000000000000000000000001010000 M
#42
0J
#43
b00000000000000000000000001011000 '
b00000000000000000000000001010100 (
1J
b00000000000000000000000001010100 M
#44
0J
#45
b00000000000000000000000001011100 '
b00000000000000000000000001011000 (
1J
b00000000000000000000000001011000 M
#46
0J
#47
b00000000000000000000000001100000 '
b00000000000000000000000001011100 (
1J
b00000000000000000000000001011100 M
#48
0J
#49
b00000000000000000000000001100100 '
b00000000000000000000000001100000 (
1J
b00000000000000000000000001100000 M
#50
0J
#51
b00000000000000000000000001101000 '
b00000000000000000000000001100100 (
1J
b00000000000000000000000001100100 M
#52
0J
#53
b00000000000000000000000001101100 '
b00000000000000000000000001101000 (
1J
b00000000000000000000000001101000 M
#54
0J
#55
b00000000000000000000000001110000 '
b00000000000000000000000001101100 (
1J
b00000000000000000000000001101100 M
#56
0J
#57
b00000000000000000000000001110100 '
b00000000000000000000000001110000 (
1J
b00000000000000000000000001110000 M
#58
0J
#59
b00000000000000000000000001111000 '
b00000000000000000000000001110100 (
1J
b00000000000000000000000001110100 M
#60
0J
#61
b00000000000000000000000001111100 '
b00000000000000000000000001111000 (
1J
b00000000000000000000000001111000 M
#62
0J
#63
b00000000000000000000000010000000 '
b00000000000000000000000001111100 (
1J
b00000000000000000000000001111100 M
#64
0J
#65
b00000000000000000000000010000100 '
b00000000000000000000000010000000 (
1J
b00000000000000000000000010000000 M
#66
0J
#67
b00000000000000000000000010001000 '
b00000000000000000000000010000100 (
1J
b00000000000000000000000010000100 M
#68
0J
#69
b00000000000000000000000010001100 '
b00000000000000000000000010001000 (
1J
b00000000000000000000000010001000 M
#70
0J
#71
b00000000000000000000000010010000 '
b00000000000000000000000010001100 (
1J
b00000000000000000000000010001100 M
#72
0J
#73
b00000000000000000000000010010100 '
b00000000000000000000000010010000 (
1J
b00000000000000000000000010010000 M
#74
0J
#75
b00000000000000000000000010011000 '
b00000000000000000000000010010100 (
1J
b00000000000000000000000010010100 M
#76
0J
#77
b00000000000000000000000010011100 '
b00000000000000000000000010011000 (
1J
b00000000000000000000000010011000 M
#78
0J
#79
b00000000000000000000000010100000 '
b00000000000000000000000010011100 (
1J
b00000000000000000000000010011100 M
#80
0J
#81
b00000000000000000000000010100100 '
b00000000000000000000000010100000 (
1J
b00000000000000000000000010100000 M
#82
0J
#83
b00000000000000000000000010101000 '
b00000000000000000000000010100100 (
1J
b00000000000000000000000010100100 M
#84
0J
#85
b00000000000000000000000010101100 '
b00000000000000000000000010101000 (
1J
b00000000000000000000000010101000 M
#86
0J
#87
b00000000000000000000000010110000 '
b00000000000000000000000010101100 (
1J
b00000000000000000000000010101100 M
#88
0J
#89
b00000000000000000000000010110100 '
b00000000000000000000000010110000 (
1J
b00000000000000000000000010110000 M
#90
0J
#91
b00000000000000000000000010111000 '
b00000000000000000000000010110100 (
1J
b00000000000000000000000010110100 M
#92
0J
#93
b00000000000000000000000010111100 '
b00000000000000000000000010111000 (
1J
b00000000000000000000000010111000 M
#94
0J
#95
b00000000000000000000000011000000 '
b00000000000000000000000010111100 (
1J
b00000000000000000000000010111100 M
#96
0J
#97
b00000000000000000000000011000100 '
b00000000000000000000000011000000 (
1J
b00000000000000000000000011000000 M
#98
0J
#99
b00000000000000000000000011001000 '
b00000000000000000000000011000100 (
1J
b00000000000000000000000011000100 M
#100
0J
#101
b00000000000000000000000011001100 '
b00000000000000000000000011001000 (
1J
b00000000000000000000000011001000 M
#102
0J
#103
b00000000000000000000000011010000 '
b00000000000000000000000011001100 (
1J
b00000000000000000000000011001100 M
#104
0J
#105
b00000000000000000000000011010100 '
b00000000000000000000000011010000 (
1J
b00000000000000000000000011010000 M
#106
0J
#107
b00000000000000000000000011011000 '
b00000000000000000000000011010100 (
1J
b00000000000000000000000011010100 M
#108
0J
#109
b00000000000000000000000011011100 '
b00000000000000000000000011011000 (
1J
b00000000000000000000000011011000 M
#110
0J
#111
b00000000000000000000000011100000 '
b00000000000000000000000011011100 (
1J
b00000000000000000000000011011100 M
#112
0J
#113
b00000000000000000000000011100100 '
b00000000000000000000000011100000 (
1J
b00000000000000000000000011100000 M
#114
0J
#115
b00000000000000000000000011101000 '
b00000000000000000000000011100100 (
1J
b00000000000000000000000011100100 M
#116
0J
#117
b00000000000000000000000011101100 '
b00000000000000000000000011101000 (
1J
b00000000000000000000000011101000 M
#118
0J
#119
b00000000000000000000000011110000 '
b00000000000000000000000011101100 (
1J
b00000000000000000000000011101100 M
#120
0J
#121
b00000000000000000000000011110100 '
b00000000000000000000000011110000 (
1J
b00000000000000000000000011110000 M
#122
0J
#123
b00000000000000000000000011111000 '
b00000000000000000000000011110100 (
1J
b00000000000000000000000011110100 M
#124
0J
#125
b00000000000000000000000011111100 '
b00000000000000000000000011111000 (
1J
b00000000000000000000000011111000 M
#126
0J
#127
b00000000000000000000000100000000 '
b00000000000000000000000011111100 (
1J
b00000000000000000000000011111100 M
#128
0J
#129
b00000000000000000000000100000100 '
b00000000000000000000000100000000 (
1J
b00000000000000000000000100000000 M
#130
0J
#131
b00000000000000000000000100001000 '
b00000000000000000000000100000100 (
1J
b00000000000000000000000100000100 M
#132
0J
#133
b00000000000000000000000100001100 '
b00000000000000000000000100001000 (
1J
b00000000000000000000000100001000 M
#134
0J
#135
b00000000000000000000000100010000 '
b00000000000000000000000100001100 (
1J
b00000000000000000000000100001100 M
#136
0J
#137
b00000000000000000000000100010100 '
b00000000000000000000000100010000 (
1J
b00000000000000000000000100010000 M
#138
0J
#139
b00000000000000000000000100011000 '
b00000000000000000000000100010100 (
1J
b00000000000000000000000100010100 M
#140
0J
#141
b00000000000000000000000100011100 '
b00000000000000000000000100011000 (
1J
b00000000000000000000000100011000 M
#142
0J
#143
b00000000000000000000000100100000 '
b00000000000000000000000100011100 (
1J
b00000000000000000000000100011100 M
#144
0J
#145
b00000000000000000000000100100100 '
b00000000000000000000000100100000 (
1J
b00000000000000000000000100100000 M
#146
0J
#147
b00000000000000000000000100101000 '
b00000000000000000000000100100100 (
1J
b00000000000000000000000100100100 M
#148
0J
#149
b00000000000000000000000100101100 '
b00000000000000000000000100101000 (
1J
b00000000000000000000000100101000 M
#150
0J
#151
b00000000000000000000000100110000 '
b00000000000000000000000100101100 (
1J
b00000000000000000000000100101100 M
#152
0J
#153
b00000000000000000000000100110100 '
b00000000000000000000000100110000 (
1J
b00000000000000000000000100110000 M
#154
0J
#155
b00000000000000000000000100111000 '
b00000000000000000000000100110100 (
1J
b00000000000000000000000100110100 M
#156
0J
#157
b00000000000000000000000100111100 '
b00000000000000000000000100111000 (
1J
b00000000000000000000000100111000 M
#158
0J
#159
b00000000000000000000000101000000 '
b00000000000000000000000100111100 (
1J
b00000000000000000000000100111100 M
#160
0J
#161
b00000000000000000000000101000100 '
b00000000000000000000000101000000 (
1J
b00000000000000000000000101000000 M
#162
0J
#163
b00000000000000000000000101001000 '
b00000000000000000000000101000100 (
1J
b00000000000000000000000101000100 M
#164
0J
#165
b00000000000000000000000101001100 '
b00000000000000000000000101001000 (
1J
b00000000000000000000000101001000 M
#166
0J
#167
b00000000000000000000000101010000 '
b00000000000000000000000101001100 (
1J
b00000000000000000000000101001100 M
#168
0J
#169
b00000000000000000000000101010100 '
b00000000000000000000000101010000 (
1J
b00000000000000000000000101010000 M
#170
0J
#171
b00000000000000000000000101011000 '
b00000000000000000000000101010100 (
1J
b00000000000000000000000101010100 M
#172
0J
#173
b00000000000000000000000101011100 '
b00000000000000000000000101011000 (
1J
b00000000000000000000000101011000 M
#174
0J
#175
b00000000000000000000000101100000 '
b00000000000000000000000101011100 (
1J
b00000000000000000000000101011100 M
#176
0J
#177
b00000000000000000000000101100100 '
b00000000000000000000000101100000 (
1J
b00000000000000000000000101100000 M
#178
0J
#179
b00000000000000000000000101101000 '
b00000000000000000000000101100100 (
1J
b00000000000000000000000101100100 M
#180
0J
#181
b00000000000000000000000101101100 '
b00000000000000000000000101101000 (
1J
b00000000000000000000000101101000 M
#182
0J
#183
b00000000000000000000000101110000 '
b00000000000000000000000101101100 (
1J
b00000000000000000000000101101100 M
#184
0J
#185
b00000000000000000000000101110100 '
b00000000000000000000000101110000 (
1J
b00000000000000000000000101110000 M
#186
0J
#187
b00000000000000000000000101111000 '
b00000000000000000000000101110100 (
1J
b00000000000000000000000101110100 M
#188
0J
#189
b00000000000000000000000101111100 '
b00000000000000000000000101111000 (
1J
b00000000000000000000000101111000 M
#190
0J
#191
b00000000000000000000000110000000 '
b00000000000000000000000101111100 (
1J
b00000000000000000000000101111100 M
#192
0J
#193
b00000000000000000000000110000100 '
b00000000000000000000000110000000 (
1J
b00000000000000000000000110000000 M
#194
0J
#195
b00000000000000000000000110001000 '
b00000000000000000000000110000100 (
1J
b00000000000000000000000110000100 M
#196
0J
#197
b00000000000000000000000110001100 '
b00000000000000000000000110001000 (
1J
b00000000000000000000000110001000 M
#198
0J
#199
b00000000000000000000000110010000 '
b00000000000000000000000110001100 (
1J
b00000000000000000000000110001100 M
